MANIFEST.in
README.rst
setup.py
adi/__init__.py
adi.bookmark.egg-info/PKG-INFO
adi.bookmark.egg-info/SOURCES.txt
adi.bookmark.egg-info/dependency_links.txt
adi.bookmark.egg-info/entry_points.txt
adi.bookmark.egg-info/namespace_packages.txt
adi.bookmark.egg-info/not-zip-safe
adi.bookmark.egg-info/requires.txt
adi.bookmark.egg-info/top_level.txt
adi/bookmark/__init__.py
adi/bookmark/configure.zcml
adi/bookmark/interfaces.py
adi/bookmark/browser/__init__.py
adi/bookmark/browser/configure.zcml
adi/bookmark/browser/resources/main.js
adi/bookmark/profiles/default/browserlayer.xml
adi/bookmark/profiles/default/cssregistry.xml
adi/bookmark/profiles/default/jsregistry.xml
adi/bookmark/profiles/default/metadata.xml
adi/bookmark/profiles/default/skins.xml
adi/bookmark/skins/adi_bookmark/adi_bookmark.pt
docs/CHANGES.rst
docs/INSTALL.rst
docs/USAGE.rst