Metadata-Version: 1.1
Name: adi.bookmark
Version: 0.2
Summary: Store bookmarks to a Plone-site or -folder.
Home-page: https://github.com/ida/adi.bookmark
Author: Ida Ebkes
Author-email: contact@ida-ebkes.eu
License: GPL
Platform: UNKNOWN
Classifier: Framework :: Plone
Classifier: Framework :: Plone :: 3.2
Classifier: Framework :: Plone :: 3.3
Classifier: Framework :: Plone :: 4.0
Classifier: Framework :: Plone :: 4.1
Classifier: Framework :: Plone :: 4.2
Classifier: Framework :: Plone :: 4.3
Classifier: Programming Language :: Python
